mutwo/core_configurations/__init__.py
mutwo/core_constants/__init__.py
mutwo/core_converters/__init__.py
mutwo/core_converters/abc.py
mutwo/core_converters/configurations.py
mutwo/core_converters/parsers.py
mutwo/core_converters/tempos.py
mutwo/core_events/__init__.py
mutwo/core_events/abc.py
mutwo/core_events/basic.py
mutwo/core_events/configurations.py
mutwo/core_events/envelopes.py
mutwo/core_events/patchparameters.py
mutwo/core_parameters/__init__.py
mutwo/core_parameters/abc.py
mutwo/core_parameters/configurations.py
mutwo/core_parameters/durations.py
mutwo/core_parameters/tempos.py
mutwo/core_utilities/__init__.py
mutwo/core_utilities/configurations.py
mutwo/core_utilities/decorators.py
mutwo/core_utilities/exceptions.py
mutwo/core_utilities/mutwo.py
mutwo/core_utilities/tests.py
mutwo/core_utilities/tools.py
mutwo/core_version/__init__.py
mutwo.core-2.0.0.dist-info/LICENSE
mutwo.core-2.0.0.dist-info/METADATA
mutwo.core-2.0.0.dist-info/WHEEL
mutwo.core-2.0.0.dist-info/top_level.txt
mutwo.core-2.0.0.dist-info/RECORD
