Metadata-Version: 2.1
Name: mutwo.core
Version: 2.0.0
Summary: core library for event based framework mutwo
Home-page: https://github.com/mutwo-org/mutwo.core
Author: Levin Eric Zimmermann, Tim Pauli
Author-email: levin.eric.zimmermann@posteo.eu, tim.pauli@folkwang-uni.de
License: GPL
Project-URL: Documentation, https://mutwo-org.github.io
Classifier: Development Status :: 5 - Production/Stable
Classifier: Intended Audience :: Developers
Classifier: Intended Audience :: End Users/Desktop
Classifier: Intended Audience :: Education
Classifier: License :: OSI Approved :: GNU General Public License v3 or later (GPLv3+)
Classifier: Operating System :: Unix
Classifier: Programming Language :: Python :: 3 :: Only
Classifier: Programming Language :: Python :: 3.10
Classifier: Programming Language :: Python :: 3.11
Classifier: Topic :: Artistic Software
Classifier: Topic :: Multimedia
Classifier: Topic :: Multimedia :: Sound/Audio
Classifier: Topic :: Multimedia :: Sound/Audio :: MIDI
Classifier: Topic :: Software Development
Classifier: Topic :: Software Development :: Libraries
Classifier: Topic :: Software Development :: Libraries :: Python Modules
Requires-Python: >=3.10, <4
License-File: LICENSE
Requires-Dist: python-ranges <2.0.0,>=1.2.0
Provides-Extra: testing
Requires-Dist: pytest >=7.1.1 ; extra == 'testing'
